{
  "data": {
    "article": {},
    "attachments": {},
    "author_id": "1436287470207832064",
    "context_annotations": [
      {
        "domain": {
          "description": "Named people in the world like Nelson Mandela",
          "id": "10",
          "name": "Person"
        },
        "entity": {
          "description": "Sadiq Khan",
          "id": "844909864316940288",
          "name": "Sadiq Khan"
        }
      },
      {
        "domain": {
          "description": "Politicians in the world, like Joe Biden",
          "id": "35",
          "name": "Politician"
        },
        "entity": {
          "description": "Sadiq Khan",
          "id": "844909864316940288",
          "name": "Sadiq Khan"
        }
      },
      {
        "domain": {
          "description": "A taxonomy of user interests. ",
          "id": "131",
          "name": "Unified Twitter Taxonomy"
        },
        "entity": {
          "description": "Sadiq Khan",
          "id": "844909864316940288",
          "name": "Sadiq Khan"
        }
      },
      {
        "domain": {
          "description": "A taxonomy of user interests. ",
          "id": "131",
          "name": "Unified Twitter Taxonomy"
        },
        "entity": {
          "description": "Politics",
          "id": "847878884917886977",
          "name": "Politics"
        }
      },
      {
        "domain": {
          "description": "A taxonomy of user interests. ",
          "id": "131",
          "name": "Unified Twitter Taxonomy"
        },
        "entity": {
          "description": "Politician",
          "id": "1070032753834438656",
          "name": "Political figures"
        }
      },
      {
        "domain": {
          "description": "Cities around the world",
          "id": "156",
          "name": "Cities"
        },
        "entity": {
          "description": "london",
          "id": "855412191050121217",
          "name": "London"
        }
      }
    ],
    "conversation_id": "2061582597080465803",
    "created_at": "2026-06-01T22:56:08.000Z",
    "edit_controls": {
      "editable_until": "2026-06-01T23:56:08.000Z",
      "edits_remaining": 5,
      "is_edit_eligible": false
    },
    "edit_history_tweet_ids": [
      "2061582597080465803"
    ],
    "entities": {
      "mentions": [
        {
          "end": 17,
          "id": "14700117",
          "start": 3,
          "username": "MayorofLondon"
        }
      ]
    },
    "geo": {},
    "id": "2061582597080465803",
    "lang": "en",
    "note_tweet": {
      "entities": {}
    },
    "possibly_sensitive": false,
    "public_metrics": {
      "bookmark_count": 0,
      "impression_count": 0,
      "like_count": 0,
      "quote_count": 0,
      "reply_count": 0,
      "retweet_count": 79
    },
    "referenced_tweets": [
      {
        "id": "2061489547888771201",
        "type": "retweeted"
      }
    ],
    "reply_settings": "mentionedUsers",
    "text": "RT @MayorofLondon: This Pride Month, London stands with our LGBTQI+ communities here and around the world.\n\nI look forward to seeing hundre…"
  },
  "includes": {
    "tweets": [
      {
        "article": {},
        "attachments": {},
        "author_id": "1436287470207832064",
        "context_annotations": [
          {
            "domain": {
              "description": "Named people in the world like Nelson Mandela",
              "id": "10",
              "name": "Person"
            },
            "entity": {
              "description": "Sadiq Khan",
              "id": "844909864316940288",
              "name": "Sadiq Khan"
            }
          },
          {
            "domain": {
              "description": "Politicians in the world, like Joe Biden",
              "id": "35",
              "name": "Politician"
            },
            "entity": {
              "description": "Sadiq Khan",
              "id": "844909864316940288",
              "name": "Sadiq Khan"
            }
          },
          {
            "domain": {
              "description": "A taxonomy of user interests. ",
              "id": "131",
              "name": "Unified Twitter Taxonomy"
            },
            "entity": {
              "description": "Sadiq Khan",
              "id": "844909864316940288",
              "name": "Sadiq Khan"
            }
          },
          {
            "domain": {
              "description": "A taxonomy of user interests. ",
              "id": "131",
              "name": "Unified Twitter Taxonomy"
            },
            "entity": {
              "description": "Politics",
              "id": "847878884917886977",
              "name": "Politics"
            }
          },
          {
            "domain": {
              "description": "A taxonomy of user interests. ",
              "id": "131",
              "name": "Unified Twitter Taxonomy"
            },
            "entity": {
              "description": "Politician",
              "id": "1070032753834438656",
              "name": "Political figures"
            }
          },
          {
            "domain": {
              "description": "Cities around the world",
              "id": "156",
              "name": "Cities"
            },
            "entity": {
              "description": "london",
              "id": "855412191050121217",
              "name": "London"
            }
          }
        ],
        "conversation_id": "2061582597080465803",
        "created_at": "2026-06-01T22:56:08.000Z",
        "edit_controls": {
          "editable_until": "2026-06-01T23:56:08.000Z",
          "edits_remaining": 5,
          "is_edit_eligible": false
        },
        "edit_history_tweet_ids": [
          "2061582597080465803"
        ],
        "entities": {
          "mentions": [
            {
              "end": 17,
              "id": "14700117",
              "start": 3,
              "username": "MayorofLondon"
            }
          ]
        },
        "geo": {},
        "id": "2061582597080465803",
        "lang": "en",
        "note_tweet": {
          "entities": {}
        },
        "possibly_sensitive": false,
        "public_metrics": {
          "bookmark_count": 0,
          "impression_count": 0,
          "like_count": 0,
          "quote_count": 0,
          "reply_count": 0,
          "retweet_count": 79
        },
        "referenced_tweets": [
          {
            "id": "2061489547888771201",
            "type": "retweeted"
          }
        ],
        "reply_settings": "mentionedUsers",
        "text": "RT @MayorofLondon: This Pride Month, London stands with our LGBTQI+ communities here and around the world.\n\nI look forward to seeing hundre…"
      },
      {
        "article": {},
        "attachments": {},
        "author_id": "14700117",
        "context_annotations": [
          {
            "domain": {
              "description": "A taxonomy of user interests. ",
              "id": "131",
              "name": "Unified Twitter Taxonomy"
            },
            "entity": {
              "id": "1332033569116459008",
              "name": "London"
            }
          },
          {
            "domain": {
              "description": "For local-level news entities",
              "id": "171",
              "name": "Local News"
            },
            "entity": {
              "id": "1332033569116459008",
              "name": "London"
            }
          },
          {
            "domain": {
              "description": "Named people in the world like Nelson Mandela",
              "id": "10",
              "name": "Person"
            },
            "entity": {
              "description": "Sadiq Khan",
              "id": "844909864316940288",
              "name": "Sadiq Khan"
            }
          },
          {
            "domain": {
              "description": "Politicians in the world, like Joe Biden",
              "id": "35",
              "name": "Politician"
            },
            "entity": {
              "description": "Sadiq Khan",
              "id": "844909864316940288",
              "name": "Sadiq Khan"
            }
          },
          {
            "domain": {
              "description": "A taxonomy of user interests. ",
              "id": "131",
              "name": "Unified Twitter Taxonomy"
            },
            "entity": {
              "description": "Sadiq Khan",
              "id": "844909864316940288",
              "name": "Sadiq Khan"
            }
          },
          {
            "domain": {
              "description": "A taxonomy of user interests. ",
              "id": "131",
              "name": "Unified Twitter Taxonomy"
            },
            "entity": {
              "description": "Politics",
              "id": "847878884917886977",
              "name": "Politics"
            }
          },
          {
            "domain": {
              "description": "A taxonomy of user interests. ",
              "id": "131",
              "name": "Unified Twitter Taxonomy"
            },
            "entity": {
              "description": "Politician",
              "id": "1070032753834438656",
              "name": "Political figures"
            }
          },
          {
            "domain": {
              "description": "Cities around the world",
              "id": "156",
              "name": "Cities"
            },
            "entity": {
              "description": "london",
              "id": "855412191050121217",
              "name": "London"
            }
          }
        ],
        "conversation_id": "2061489547888771201",
        "created_at": "2026-06-01T16:46:23.000Z",
        "edit_controls": {
          "editable_until": "2026-06-01T17:46:23.000Z",
          "edits_remaining": 5,
          "is_edit_eligible": true
        },
        "edit_history_tweet_ids": [
          "2061489547888771201"
        ],
        "entities": {},
        "geo": {},
        "id": "2061489547888771201",
        "lang": "en",
        "note_tweet": {
          "entities": {}
        },
        "possibly_sensitive": false,
        "public_metrics": {
          "bookmark_count": 27,
          "impression_count": 343410,
          "like_count": 753,
          "quote_count": 59,
          "reply_count": 0,
          "retweet_count": 79
        },
        "reply_settings": "mentionedUsers",
        "text": "This Pride Month, London stands with our LGBTQI+ communities here and around the world.\n\nI look forward to seeing hundreds of thousands of Londoners and visitors taking to our streets in celebration and solidarity for Pride in London on Saturday, 4 July."
      }
    ],
    "users": [
      {
        "created_at": "2021-09-10T11:17:02.000Z",
        "description": "开发者，构建社区、AI工具和规模化的数据收集 | \n\n说话含喵量巨大🤯的高二在校生。 | \n你看白雪人间 你看寒夜无岸 \n|\n跨圈列表私信我，开贴喷没有用。\n没看到私信可以随便找个帖子回复下提醒我\n\n要饭：https://t.co/aMQp3GpkVJ\n\n私人 @lunayurari ❤️ @tsgostar",
        "entities": {
          "description": {
            "mentions": [
              {
                "end": 142,
                "start": 131,
                "username": "lunayurari"
              },
              {
                "end": 155,
                "start": 146,
                "username": "tsgostar"
              }
            ],
            "urls": [
              {
                "display_url": "sink.wuyuan.dev/afd",
                "end": 126,
                "expanded_url": "https://sink.wuyuan.dev/afd",
                "start": 103,
                "url": "https://t.co/aMQp3GpkVJ"
              }
            ]
          },
          "url": {
            "urls": [
              {
                "display_url": "wuyuan.dev",
                "end": 23,
                "expanded_url": "https://wuyuan.dev",
                "start": 0,
                "url": "https://t.co/QRKaQrisQX"
              }
            ]
          }
        },
        "id": "1436287470207832064",
        "location": "zh-CN 🌏",
        "name": "孙悟元",
        "pinned_tweet_id": "2055959051016745227",
        "profile_image_url": "https://pbs.twimg.com/profile_images/2060988547063259136/k51eG-qk_normal.jpg",
        "protected": false,
        "public_metrics": {
          "followers_count": 734,
          "following_count": 315,
          "like_count": 5029,
          "listed_count": 5,
          "media_count": 298,
          "tweet_count": 1507
        },
        "url": "https://t.co/QRKaQrisQX",
        "username": "wuyuandev",
        "verified": true
      },
      {
        "created_at": "2008-05-08T13:23:35.000Z",
        "description": "Husband, father, and Mayor of the greatest city in the world. He/Him. Tweets before 9 May 2016 are from the previous Mayor.",
        "entities": {
          "url": {
            "urls": [
              {
                "display_url": "instagram.com/mayorofldn",
                "end": 23,
                "expanded_url": "https://www.instagram.com/mayorofldn",
                "start": 0,
                "url": "https://t.co/UsQ3SpuwEs"
              }
            ]
          }
        },
        "id": "14700117",
        "location": "London",
        "name": "Mayor of London, Sadiq Khan",
        "pinned_tweet_id": "1968213178619445492",
        "profile_image_url": "https://pbs.twimg.com/profile_images/2053402263805104133/adMwbufu_normal.jpg",
        "protected": false,
        "public_metrics": {
          "followers_count": 2889453,
          "following_count": 991,
          "like_count": 301,
          "listed_count": 8800,
          "media_count": 9566,
          "tweet_count": 35835
        },
        "url": "https://t.co/UsQ3SpuwEs",
        "username": "MayorofLondon",
        "verified": true
      }
    ]
  }
}