{
  "data": {
    "article": {},
    "attachments": {},
    "author_id": "1436287470207832064",
    "conversation_id": "2061450437195370805",
    "created_at": "2026-06-01T14:10:59.000Z",
    "edit_controls": {
      "editable_until": "2026-06-01T15:10:59.000Z",
      "edits_remaining": 5,
      "is_edit_eligible": false
    },
    "edit_history_tweet_ids": [
      "2061450440810905776"
    ],
    "entities": {
      "urls": [
        {
          "description": "严守官方发行标准。我们的介质在刻录前均经过严格的 SHA512 哈希值校验，坚决杜绝第三方非官方源中可能包含的“夹带私货”，确保您得到的是原汁原味的 Debian 系统。 U盘套装不仅用于安装，还包含完整的 Live 桌面环境。当您的主系统崩溃、GRUB 引导损坏或忘记密码时，插上它免安装即可进入图形界面，成为您手中强大的“应急瑞士军刀”。 免责声明：Debian 是自由软件，按“原样”（AS IS）提供。社区志愿者致力于提供高质量的服务，但依据自由软件许可证（如 GPL），软件不提供任何明示或暗示的担保，包括但不限于对适销性或特定用途适用性的担保。ASYS科技仅分发Debian，与Debian项目无任何商业合作或隶属关系。",
          "display_url": "asystech.cn/pc/debian.html",
          "end": 23,
          "expanded_url": "https://asystech.cn/pc/debian.html",
          "start": 0,
          "status": 200,
          "title": "Debian 安装介质详情 - 赛思科技",
          "unwound_url": "https://asystech.cn/pc/debian.html",
          "url": "https://t.co/aOWdhKtMO1"
        }
      ]
    },
    "geo": {},
    "id": "2061450440810905776",
    "in_reply_to_user_id": "1436287470207832064",
    "lang": "zxx",
    "note_tweet": {
      "entities": {}
    },
    "possibly_sensitive": false,
    "public_metrics": {
      "bookmark_count": 0,
      "impression_count": 0,
      "like_count": 0,
      "quote_count": 0,
      "reply_count": 0,
      "retweet_count": 0
    },
    "referenced_tweets": [
      {
        "id": "2061450437195370805",
        "type": "replied_to"
      }
    ],
    "reply_settings": "everyone",
    "text": "https://t.co/aOWdhKtMO1"
  },
  "includes": {
    "media": [
      {
        "height": 1196,
        "media_key": "3_2061450429993795584",
        "public_metrics": {},
        "type": "photo",
        "url": "https://pbs.twimg.com/media/HJu-PnnbQAATdOP.jpg",
        "width": 1196
      }
    ],
    "tweets": [
      {
        "article": {},
        "attachments": {},
        "author_id": "1436287470207832064",
        "conversation_id": "2061450437195370805",
        "created_at": "2026-06-01T14:10:59.000Z",
        "edit_controls": {
          "editable_until": "2026-06-01T15:10:59.000Z",
          "edits_remaining": 5,
          "is_edit_eligible": false
        },
        "edit_history_tweet_ids": [
          "2061450440810905776"
        ],
        "entities": {
          "urls": [
            {
              "description": "严守官方发行标准。我们的介质在刻录前均经过严格的 SHA512 哈希值校验，坚决杜绝第三方非官方源中可能包含的“夹带私货”，确保您得到的是原汁原味的 Debian 系统。 U盘套装不仅用于安装，还包含完整的 Live 桌面环境。当您的主系统崩溃、GRUB 引导损坏或忘记密码时，插上它免安装即可进入图形界面，成为您手中强大的“应急瑞士军刀”。 免责声明：Debian 是自由软件，按“原样”（AS IS）提供。社区志愿者致力于提供高质量的服务，但依据自由软件许可证（如 GPL），软件不提供任何明示或暗示的担保，包括但不限于对适销性或特定用途适用性的担保。ASYS科技仅分发Debian，与Debian项目无任何商业合作或隶属关系。",
              "display_url": "asystech.cn/pc/debian.html",
              "end": 23,
              "expanded_url": "https://asystech.cn/pc/debian.html",
              "start": 0,
              "status": 200,
              "title": "Debian 安装介质详情 - 赛思科技",
              "unwound_url": "https://asystech.cn/pc/debian.html",
              "url": "https://t.co/aOWdhKtMO1"
            }
          ]
        },
        "geo": {},
        "id": "2061450440810905776",
        "in_reply_to_user_id": "1436287470207832064",
        "lang": "zxx",
        "note_tweet": {
          "entities": {}
        },
        "possibly_sensitive": false,
        "public_metrics": {
          "bookmark_count": 0,
          "impression_count": 0,
          "like_count": 0,
          "quote_count": 0,
          "reply_count": 0,
          "retweet_count": 0
        },
        "referenced_tweets": [
          {
            "id": "2061450437195370805",
            "type": "replied_to"
          }
        ],
        "reply_settings": "everyone",
        "text": "https://t.co/aOWdhKtMO1"
      },
      {
        "article": {},
        "attachments": {
          "media_keys": [
            "3_2061450429993795584"
          ]
        },
        "author_id": "1436287470207832064",
        "context_annotations": [
          {
            "domain": {
              "description": "Categories within Brand Verticals that narrow down the scope of Brands",
              "id": "46",
              "name": "Business Taxonomy"
            },
            "entity": {
              "description": "Brands, companies, advertisers and every non-person handle with the profit intent related to softwares, apps, communication equipments, hardwares",
              "id": "1557697333571112960",
              "name": "Technology Business"
            }
          },
          {
            "domain": {
              "description": "Entity Service top level domain, every item that is in Entity Service should be in this domain",
              "id": "30",
              "name": "Entities [Entity Service]"
            },
            "entity": {
              "description": "Technology and computing",
              "id": "848920371311001600",
              "name": "Technology"
            }
          },
          {
            "domain": {
              "description": "A grouping of interests and hobbies entities, like Novelty Food or Destinations",
              "id": "66",
              "name": "Interests and Hobbies Category"
            },
            "entity": {
              "description": "Linux",
              "id": "848959431836487680",
              "name": "Linux"
            }
          },
          {
            "domain": {
              "description": "A taxonomy of user interests. ",
              "id": "131",
              "name": "Unified Twitter Taxonomy"
            },
            "entity": {
              "description": "Linux",
              "id": "848959431836487680",
              "name": "Linux"
            }
          }
        ],
        "conversation_id": "2061450437195370805",
        "created_at": "2026-06-01T14:10:58.000Z",
        "edit_controls": {
          "editable_until": "2026-06-01T15:10:58.000Z",
          "edits_remaining": 5,
          "is_edit_eligible": false
        },
        "edit_history_tweet_ids": [
          "2061450437195370805"
        ],
        "entities": {
          "urls": [
            {
              "display_url": "pic.x.com/q7OgO7gtvG",
              "end": 90,
              "expanded_url": "https://x.com/wuyuandev/status/2061450437195370805/photo/1",
              "media_key": "3_2061450429993795584",
              "start": 67,
              "url": "https://t.co/q7OgO7gtvG"
            },
            {
              "display_url": "x.com/wuyuandev/stat…",
              "end": 114,
              "expanded_url": "https://twitter.com/wuyuandev/status/2061085425759064493",
              "start": 91,
              "url": "https://t.co/uos1EnSIEA"
            }
          ]
        },
        "geo": {},
        "id": "2061450437195370805",
        "lang": "zh",
        "note_tweet": {
          "entities": {}
        },
        "possibly_sensitive": false,
        "public_metrics": {
          "bookmark_count": 0,
          "impression_count": 0,
          "like_count": 0,
          "quote_count": 0,
          "reply_count": 1,
          "retweet_count": 0
        },
        "referenced_tweets": [
          {
            "id": "2061085425759064493",
            "type": "quoted"
          }
        ],
        "reply_settings": "everyone",
        "text": "以防你不知道，Debian认证过的光盘供应商ASYS推出了补佳乐版本的Debian 13安装光盘，预售39元包邮。\n\n纯血xyn系统 https://t.co/q7OgO7gtvG https://t.co/uos1EnSIEA"
      }
    ],
    "users": [
      {
        "created_at": "2021-09-10T11:17:02.000Z",
        "description": "开发者，构建社区、AI工具和规模化的数据收集 | \n\n说话含喵量巨大🤯的高二在校生。 | \n你看白雪人间 你看寒夜无岸 \n|\n跨圈列表私信我，开贴喷没有用。\n没看到私信可以随便找个帖子回复下提醒我\n\n要饭：https://t.co/aMQp3GpkVJ\n\n私人 @lunayurari ❤️ @tsgostar",
        "entities": {
          "description": {
            "mentions": [
              {
                "end": 142,
                "start": 131,
                "username": "lunayurari"
              },
              {
                "end": 155,
                "start": 146,
                "username": "tsgostar"
              }
            ],
            "urls": [
              {
                "display_url": "sink.wuyuan.dev/afd",
                "end": 126,
                "expanded_url": "https://sink.wuyuan.dev/afd",
                "start": 103,
                "url": "https://t.co/aMQp3GpkVJ"
              }
            ]
          },
          "url": {
            "urls": [
              {
                "display_url": "wuyuan.dev",
                "end": 23,
                "expanded_url": "https://wuyuan.dev",
                "start": 0,
                "url": "https://t.co/QRKaQrisQX"
              }
            ]
          }
        },
        "id": "1436287470207832064",
        "location": "zh-CN 🌏",
        "name": "孙悟元",
        "pinned_tweet_id": "2055959051016745227",
        "profile_image_url": "https://pbs.twimg.com/profile_images/2060988547063259136/k51eG-qk_normal.jpg",
        "protected": false,
        "public_metrics": {
          "followers_count": 727,
          "following_count": 301,
          "like_count": 5009,
          "listed_count": 5,
          "media_count": 297,
          "tweet_count": 1487
        },
        "url": "https://t.co/QRKaQrisQX",
        "username": "wuyuandev",
        "verified": true
      }
    ]
  }
}