{
  "data": {
    "article": {},
    "attachments": {},
    "author_id": "1436287470207832064",
    "conversation_id": "2062304491664457817",
    "created_at": "2026-06-03T22:44:41.000Z",
    "edit_controls": {
      "editable_until": "2026-06-03T23:44:41.000Z",
      "edits_remaining": 5,
      "is_edit_eligible": false
    },
    "edit_history_tweet_ids": [
      "2062304491664457817"
    ],
    "entities": {
      "mentions": [
        {
          "end": 15,
          "id": "2048693394226974720",
          "start": 3,
          "username": "CCA8798suki"
        }
      ],
      "urls": [
        {
          "display_url": "mtf.wiki",
          "end": 65,
          "expanded_url": "http://mtf.wiki",
          "start": 42,
          "status": 200,
          "title": "MtF.wiki",
          "unwound_url": "https://mtf.wiki/",
          "url": "https://t.co/ECbAPbu3d2"
        }
      ]
    },
    "geo": {},
    "id": "2062304491664457817",
    "lang": "zh",
    "note_tweet": {
      "entities": {}
    },
    "possibly_sensitive": false,
    "public_metrics": {
      "bookmark_count": 0,
      "impression_count": 0,
      "like_count": 0,
      "quote_count": 0,
      "reply_count": 0,
      "retweet_count": 20
    },
    "referenced_tweets": [
      {
        "id": "2061814797843468381",
        "type": "retweeted"
      }
    ],
    "reply_settings": "everyone",
    "text": "RT @CCA8798suki: 墙内太多太多跟风吃糖的\n吃药前能不能先看一下药理\nhttps://t.co/ECbAPbu3d2和一堆pdf都是很好的渠道\n\n我已经见过包括但不限于：\n1.单吃糖不吃抗雄的(n多)\n2.吃了一段时间结果还一问三不知的\n3.一问药物相互作用根本不…"
  },
  "includes": {
    "tweets": [
      {
        "article": {},
        "attachments": {},
        "author_id": "1436287470207832064",
        "conversation_id": "2062304491664457817",
        "created_at": "2026-06-03T22:44:41.000Z",
        "edit_controls": {
          "editable_until": "2026-06-03T23:44:41.000Z",
          "edits_remaining": 5,
          "is_edit_eligible": false
        },
        "edit_history_tweet_ids": [
          "2062304491664457817"
        ],
        "entities": {
          "mentions": [
            {
              "end": 15,
              "id": "2048693394226974720",
              "start": 3,
              "username": "CCA8798suki"
            }
          ],
          "urls": [
            {
              "display_url": "mtf.wiki",
              "end": 65,
              "expanded_url": "http://mtf.wiki",
              "start": 42,
              "status": 200,
              "title": "MtF.wiki",
              "unwound_url": "https://mtf.wiki/",
              "url": "https://t.co/ECbAPbu3d2"
            }
          ]
        },
        "geo": {},
        "id": "2062304491664457817",
        "lang": "zh",
        "note_tweet": {
          "entities": {}
        },
        "possibly_sensitive": false,
        "public_metrics": {
          "bookmark_count": 0,
          "impression_count": 0,
          "like_count": 0,
          "quote_count": 0,
          "reply_count": 0,
          "retweet_count": 20
        },
        "referenced_tweets": [
          {
            "id": "2061814797843468381",
            "type": "retweeted"
          }
        ],
        "reply_settings": "everyone",
        "text": "RT @CCA8798suki: 墙内太多太多跟风吃糖的\n吃药前能不能先看一下药理\nhttps://t.co/ECbAPbu3d2和一堆pdf都是很好的渠道\n\n我已经见过包括但不限于：\n1.单吃糖不吃抗雄的(n多)\n2.吃了一段时间结果还一问三不知的\n3.一问药物相互作用根本不…"
      },
      {
        "article": {},
        "attachments": {},
        "author_id": "2048693394226974720",
        "conversation_id": "2061814797843468381",
        "created_at": "2026-06-02T14:18:49.000Z",
        "edit_controls": {
          "editable_until": "2026-06-02T15:18:49.000Z",
          "edits_remaining": 5,
          "is_edit_eligible": true
        },
        "edit_history_tweet_ids": [
          "2061814797843468381"
        ],
        "entities": {
          "urls": [
            {
              "display_url": "mtf.wiki",
              "end": 48,
              "expanded_url": "http://mtf.wiki",
              "start": 25,
              "status": 200,
              "title": "MtF.wiki",
              "unwound_url": "https://mtf.wiki/",
              "url": "https://t.co/ECbAPbu3d2"
            }
          ]
        },
        "geo": {},
        "id": "2061814797843468381",
        "lang": "zh",
        "note_tweet": {
          "entities": {
            "urls": [
              {
                "display_url": "mtf.wiki",
                "end": 48,
                "expanded_url": "http://mtf.wiki",
                "start": 25,
                "url": "https://t.co/4dAodnt5KV"
              }
            ]
          },
          "text": "墙内太多太多跟风吃糖的\n吃药前能不能先看一下药理\nhttps://t.co/4dAodnt5KV和一堆pdf都是很好的渠道\n\n我已经见过包括但不限于：\n1.单吃糖不吃抗雄的(n多)\n2.吃了一段时间结果还一问三不知的\n3.一问药物相互作用根本不知道的\n4.根本没想花心思去了解背后的东西只觉得吃糖很好玩的\n5.完全是出于好奇只在QQ群里问而不真正自己去了解完全按照别人方案来的\n6.一大堆药物混着来就怕肝不烂掉的\n7.以为刚吃药就能变成香香软软糯糯猫娘跑墙内一顿分享吸引更多跟风的人购买补佳乐的\n8.吃螺内酯还去吃高钾食物的\n9.吃螺内酯上厕所多还以为是自己前列腺退化的\n10.吃CPA完全不看累积剂量以为自己是肝王的\n11.连药商都懒得问的\n12.舌下含服以为是在舌尖下方含服的\n13.认为CPA和醋酸环丙孕酮片主要成分不一致的\n\n...还有非常多条目...\n\n吃药前看说明书不是必备环节吗\n遵医嘱按量服另说\n我反对一切盲目用药\n用药前后都应该为自己的身体负责\n本篇不适用于用药方案有风险但主要原因是家庭因素及不可抗力因素的"
        },
        "possibly_sensitive": false,
        "public_metrics": {
          "bookmark_count": 66,
          "impression_count": 12712,
          "like_count": 175,
          "quote_count": 2,
          "reply_count": 33,
          "retweet_count": 20
        },
        "reply_settings": "everyone",
        "text": "墙内太多太多跟风吃糖的\n吃药前能不能先看一下药理\nhttps://t.co/ECbAPbu3d2和一堆pdf都是很好的渠道\n\n我已经见过包括但不限于：\n1.单吃糖不吃抗雄的(n多)\n2.吃了一段时间结果还一问三不知的\n3.一问药物相互作用根本不知道的\n4.根本没想花心思去了解背后的东西只觉得吃糖很好玩的"
      }
    ],
    "users": [
      {
        "created_at": "2021-09-10T11:17:02.000Z",
        "description": "开发者，构建社区、AI工具和规模化的数据收集 | \n\n说话含喵量巨大🤯的高二在校生。 | \n你看白雪人间 你看寒夜无岸 \n|\n跨圈列表私信我，开贴喷没有用。\n没看到私信可以随便找个帖子回复下提醒我\n\n要饭：https://t.co/aMQp3GpkVJ\n\n私人 @lunayurari ❤️ @tsgostar",
        "entities": {
          "description": {
            "mentions": [
              {
                "end": 142,
                "start": 131,
                "username": "lunayurari"
              },
              {
                "end": 155,
                "start": 146,
                "username": "tsgostar"
              }
            ],
            "urls": [
              {
                "display_url": "sink.wuyuan.dev/afd",
                "end": 126,
                "expanded_url": "https://sink.wuyuan.dev/afd",
                "start": 103,
                "url": "https://t.co/aMQp3GpkVJ"
              }
            ]
          },
          "url": {
            "urls": [
              {
                "display_url": "wuyuan.dev",
                "end": 23,
                "expanded_url": "https://wuyuan.dev",
                "start": 0,
                "url": "https://t.co/QRKaQrisQX"
              }
            ]
          }
        },
        "id": "1436287470207832064",
        "location": "zh-CN 🌏",
        "name": "孙悟元",
        "pinned_tweet_id": "2055959051016745227",
        "profile_image_url": "https://pbs.twimg.com/profile_images/2060988547063259136/k51eG-qk_normal.jpg",
        "protected": false,
        "public_metrics": {
          "followers_count": 765,
          "following_count": 349,
          "like_count": 5133,
          "listed_count": 5,
          "media_count": 310,
          "tweet_count": 1559
        },
        "url": "https://t.co/QRKaQrisQX",
        "username": "wuyuandev",
        "verified": true
      },
      {
        "created_at": "2026-04-27T09:19:12.000Z",
        "description": "MTF/X🍥 | 含糖 | 年龄党+家长党 出柜2026.05.05 出厂:壹贰.零壹.零叁 | 166cm/41kg | 佛山 |  偏内向 玻璃心 双相中焦 ED GD OD | 雷伪娘、艹、Dick字眼 | 交通 科学 医学 杂圈迷 | Cpp Coder | 寻回前世互fo | 恨MSK\n前世@CCA8798",
        "entities": {
          "description": {
            "mentions": [
              {
                "end": 159,
                "start": 151,
                "username": "CCA8798"
              }
            ]
          },
          "url": {
            "urls": [
              {
                "display_url": "cca8798.com/about/",
                "end": 23,
                "expanded_url": "http://cca8798.com/about/",
                "start": 0,
                "url": "https://t.co/0gMYiKoF6B"
              }
            ]
          }
        },
        "id": "2048693394226974720",
        "location": "安东星蜗牛第一票常交易矿业太空旅行无限Co., Ltd",
        "name": "不会起名の捌拐玖捌🍥(二代目互fo寻回中)",
        "pinned_tweet_id": "2059398080643190943",
        "profile_image_url": "https://pbs.twimg.com/profile_images/2059761684500336640/bvv_7t16_normal.jpg",
        "protected": false,
        "public_metrics": {
          "followers_count": 499,
          "following_count": 534,
          "like_count": 797,
          "listed_count": 3,
          "media_count": 21,
          "tweet_count": 162
        },
        "url": "https://t.co/0gMYiKoF6B",
        "username": "CCA8798suki",
        "verified": true
      }
    ]
  }
}