{
  "data": {
    "article": {},
    "attachments": {},
    "author_id": "1436287470207832064",
    "conversation_id": "2055803370007584841",
    "created_at": "2026-05-17T00:11:33.000Z",
    "edit_controls": {
      "editable_until": "2026-05-17T01:11:33.000Z",
      "edits_remaining": 5,
      "is_edit_eligible": true
    },
    "edit_history_tweet_ids": [
      "2055803370007584841"
    ],
    "entities": {},
    "geo": {},
    "id": "2055803370007584841",
    "lang": "zh",
    "note_tweet": {
      "entities": {}
    },
    "possibly_sensitive": false,
    "public_metrics": {
      "bookmark_count": 0,
      "impression_count": 0,
      "like_count": 0,
      "quote_count": 0,
      "reply_count": 0,
      "retweet_count": 0
    },
    "reply_settings": "everyone",
    "text": "每天list里都会少一两个人，由此可以大体上窥见跨圈在x上的封号量（？）"
  },
  "includes": {
    "tweets": [
      {
        "article": {},
        "attachments": {},
        "author_id": "1436287470207832064",
        "conversation_id": "2055803370007584841",
        "created_at": "2026-05-17T00:11:33.000Z",
        "edit_controls": {
          "editable_until": "2026-05-17T01:11:33.000Z",
          "edits_remaining": 5,
          "is_edit_eligible": true
        },
        "edit_history_tweet_ids": [
          "2055803370007584841"
        ],
        "entities": {},
        "geo": {},
        "id": "2055803370007584841",
        "lang": "zh",
        "note_tweet": {
          "entities": {}
        },
        "possibly_sensitive": false,
        "public_metrics": {
          "bookmark_count": 0,
          "impression_count": 0,
          "like_count": 0,
          "quote_count": 0,
          "reply_count": 0,
          "retweet_count": 0
        },
        "reply_settings": "everyone",
        "text": "每天list里都会少一两个人，由此可以大体上窥见跨圈在x上的封号量（？）"
      }
    ],
    "users": [
      {
        "created_at": "2021-09-10T11:17:02.000Z",
        "description": "开发者 | 说话含喵量巨大 | 今年欢笑复明年，秋月春风等闲度。| 关注本喵喵！关注本喵谢谢喵！| 你看白雪人间 你看寒夜无岸\n\n没看到私信可以随便找个帖子回复下提醒我",
        "entities": {
          "url": {
            "urls": [
              {
                "display_url": "langs.ink",
                "end": 23,
                "expanded_url": "https://langs.ink",
                "start": 0,
                "url": "https://t.co/Z142BBjByr"
              }
            ]
          }
        },
        "id": "1436287470207832064",
        "location": "zh-CN 🌏",
        "name": "死与生 云与雨",
        "pinned_tweet_id": "2051211437847290211",
        "profile_image_url": "https://pbs.twimg.com/profile_images/2051553122678718464/Q_GQbOlo_normal.jpg",
        "protected": false,
        "public_metrics": {
          "followers_count": 375,
          "following_count": 227,
          "like_count": 3580,
          "listed_count": 3,
          "media_count": 204,
          "tweet_count": 1011
        },
        "url": "https://t.co/Z142BBjByr",
        "username": "wuyuandev",
        "verified": false
      }
    ]
  }
}